{
  "host": "localhost",
  "port": 3030,
  "mongodb": "mongodb://localhost:27017/invSystem",
  "public": "../public/",
  "auth": {
    "token": {
      "secret": "JMZQWvQKX2ro04M/RAj9PvDuShXBycEOx2uKuOlAMf7O0kZsNSOqCH2Kl1HLtMjy1rcSDLQb80JHDY2Jfgd4Vg=="
    },
    "local": {}
  },
  "mailgun": {
    "apiKey": "key-d64b98f2977515ff21806fbe2c27f92b",
    "domain": "sandbox90234bbf28114475b4475f6df62e30a1.mailgun.org"
  },
  "nodemailer": {
    "host": "smtp.office365.com",
    "port": "587",
    "auth": {
      "user": "MAIL_USER",
      "pass": "MAIL_PASS"
    },
    "secureConnection": "false",
    "tls": { "ciphers": "SSLv3" }
  }
}
